SecretPlots/__init__.py
SecretPlots/utils.py
SecretPlots/assemblers/__init__.py
SecretPlots/assemblers/_bars.py
SecretPlots/assemblers/_base.py
SecretPlots/assemblers/_matrix.py
SecretPlots/constants/__init__.py
SecretPlots/constants/graph.py
SecretPlots/constants/network.py
SecretPlots/constants/system.py
SecretPlots/genomics/__init__.py
SecretPlots/genomics/rnaseq.py
SecretPlots/graphs/__init__.py
SecretPlots/graphs/_graphs.py
SecretPlots/graphs/categorical.py
SecretPlots/graphs/network.py
SecretPlots/managers/__init__.py
SecretPlots/managers/_axis.py
SecretPlots/managers/_color.py
SecretPlots/managers/_extra.py
SecretPlots/managers/_grid.py
SecretPlots/managers/_object.py
SecretPlots/managers/location/__init__.py
SecretPlots/managers/location/_bars.py
SecretPlots/managers/location/_base.py
SecretPlots/managers/location/_matrix.py
SecretPlots/network/__init__.py
SecretPlots/network/graphs.py
SecretPlots/network/pathfinder.py
SecretPlots/objects/__init__.py
SecretPlots/objects/_base.py
SecretPlots/objects/matrix.py
SecretPlots/objects/network.py
SecretPlots/objects/shapes.py
tests/__init__.py
tests/test_network.py
SecretPlots-0.1.3.dist-info/LICENSE
SecretPlots-0.1.3.dist-info/METADATA
SecretPlots-0.1.3.dist-info/WHEEL
SecretPlots-0.1.3.dist-info/top_level.txt
SecretPlots-0.1.3.dist-info/RECORD
